{
  "parent": "item/handheld",
  "textures": {
    "layer0": "sow:item/scarred_diamond_sword"
  },
  "display": {
    "thirdperson_righthand": {
      "rotation": [
        0,
        -90,
        55
      ],
      "translation": [
        0,
        4.5,
        0.5
      ],
      "scale": [
        0.95625,
        0.95625,
        0.95625
      ]
    },
    "thirdperson_lefthand": {
      "rotation": [
        0,
        90,
        -55
      ],
      "translation": [
        0,
        4.5,
        0.5
      ],
      "scale": [
        0.95625,
        0.95625,
        0.95625
      ]
    },
    "firstperson_righthand": {
      "rotation": [
        0,
        -90,
        25
      ],
      "translation": [
        1.13,
        3.2,
        2.13
      ],
      "scale": [
        0.765,
        0.765,
        0.765
      ]
    },
    "firstperson_lefthand": {
      "rotation": [
        0,
        90,
        -25
      ],
      "translation": [
        1.13,
        3.2,
        2.13
      ],
      "scale": [
        0.765,
        0.765,
        0.765
      ]
    }
  }
}